llmstxt2skill/__init__.py
llmstxt2skill/cli.py
llmstxt2skill/enricher.py
llmstxt2skill/fetcher.py
llmstxt2skill/generator.py
llmstxt2skill/models.py
llmstxt2skill/parser.py
llmstxt2skill/writer.py
llmstxt2skill/llm/__init__.py
llmstxt2skill/llm/base.py
llmstxt2skill/llm/factory.py
llmstxt2skill/llm/providers/__init__.py
llmstxt2skill/llm/providers/anthropic.py
llmstxt2skill/llm/providers/databricks.py
llmstxt2skill/llm/providers/openai.py
llmstxt2skill/llm/providers/openai_compatible.py
llmstxt2skill-0.2.4.dist-info/METADATA
llmstxt2skill-0.2.4.dist-info/WHEEL
llmstxt2skill-0.2.4.dist-info/entry_points.txt
llmstxt2skill-0.2.4.dist-info/licenses/LICENSE
llmstxt2skill-0.2.4.dist-info/RECORD
