Metadata-Version: 2.4
Name: llmstxt2skill
Version: 0.2.4
Summary: Convert llms.txt to Claude Code Skill format
Project-URL: Homepage, https://github.com/akuwano/llmstxt2skill
Project-URL: Repository, https://github.com/akuwano/llmstxt2skill
Project-URL: Issues, https://github.com/akuwano/llmstxt2skill/issues
Project-URL: Changelog, https://github.com/akuwano/llmstxt2skill/blob/main/CHANGELOG.md
Author: llmstxt2skill contributors
License-Expression: Apache-2.0
License-File: LICENSE
Keywords: claude,cli,converter,llms.txt,skill
Classifier: Development Status :: 4 - Beta
Classifier: Environment :: Console
Classifier: Intended Audience :: Developers
Classifier: License :: OSI Approved :: Apache Software License
Classifier: Operating System :: OS Independent
Classifier: Programming Language :: Python :: 3
Classifier: Programming Language :: Python :: 3.11
Classifier: Programming Language :: Python :: 3.12
Classifier: Programming Language :: Python :: 3.13
Classifier: Topic :: Software Development :: Code Generators
Classifier: Topic :: Utilities
Requires-Python: >=3.11
Requires-Dist: httpx>=0.27.0
Requires-Dist: pyyaml>=6.0
Provides-Extra: dev
Requires-Dist: pytest-asyncio>=0.23; extra == 'dev'
Requires-Dist: pytest-httpx>=0.30; extra == 'dev'
Requires-Dist: pytest>=8.0; extra == 'dev'
Requires-Dist: ruff>=0.3; extra == 'dev'
